essential/__init__.py
essential/db_cli.py
essential/request_cli.py
essential/utils.py
essential_utils-0.1.0.dist-info/licenses/LICENSE
essential_utils-0.1.0.dist-info/METADATA
essential_utils-0.1.0.dist-info/WHEEL
essential_utils-0.1.0.dist-info/top_level.txt
essential_utils-0.1.0.dist-info/RECORD
