Metadata-Version: 2.4
Name: essential-utils
Version: 0.1.0
Summary: essential-utils library for database, requests, and general utilities
Author-email: IperGiove <ipergiove@gmail.com>
License: MIT
Project-URL: Homepage, https://github.com/ipergiove/essential-utils
Project-URL: Repository, https://github.com/ipergiove/essential-utils
Classifier: Programming Language :: Python :: 3
Classifier: License :: OSI Approved :: MIT License
Classifier: Operating System :: OS Independent
Requires-Python: >=3.14
License-File: LICENSE
Requires-Dist: aiosqlite>=0.21.0
Requires-Dist: curl-cffi>=0.13.0
Requires-Dist: fake-useragent>=2.2.0
Requires-Dist: httpx>=0.28.1
Requires-Dist: loguru>=0.7.3
Dynamic: license-file
